LICENSE.txt
README.md
setup.cfg
setup.py
src/goldbox/__init__.py
src/goldbox.egg-info/PKG-INFO
src/goldbox.egg-info/SOURCES.txt
src/goldbox.egg-info/dependency_links.txt
src/goldbox.egg-info/top_level.txt
src/goldbox/structures/__init__.py
src/goldbox/structures/chains.py
src/goldbox/structures/misc.py
src/goldbox/structures/trees.py
src/goldbox/tools/__init__.py
src/goldbox/tools/chaos.py
src/goldbox/tools/misc.py
src/goldbox/tools/text.py
src/goldbox/values/__init__.py
src/goldbox/values/text.py